<?xml version="1.0" encoding="utf-8"?>
<VärdepappersfondInnehav xmlns="http://schemas.fi.se/publika/vardepappersfonder/20200331">
  <Rapportinformation>
    <Kvartalsslut>2024-09-30</Kvartalsslut>
  </Rapportinformation>
  <Bolagsinformation>
    <Fondbolag_namn>Alfred Berg Kapitalforvaltning AS</Fondbolag_namn>
    <Fondbolag_institutnummer>91</Fondbolag_institutnummer>
    <Fondbolag_LEI-kod>5493008SCMZGB4WVR256</Fondbolag_LEI-kod>
  </Bolagsinformation>
  <Fondinformation>
    <Fond_institutnummer>64806</Fond_institutnummer>
    <Fond_ISIN-kod>SE0017232143</Fond_ISIN-kod>
    <Fond_namn>SPV Rente+</Fond_namn>
    <Förvaltningsavgift>
      <UtanAndelsklasser>
        <Förvaltningsavgift_fast>0.5</Förvaltningsavgift_fast>
      </UtanAndelsklasser>
    </Förvaltningsavgift>
    <Fondförmögenhet>428222395</Fondförmögenhet>
    <Likvida_medel>8509200</Likvida_medel>
    <Övriga_tillgångar_och_skulder>3339496</Övriga_tillgångar_och_skulder>
    <Standardavvikelse_24_månader>3.51</Standardavvikelse_24_månader>
    <Jämförelseindex>
      <Jämförelseindex>Jämförelseindex saknas</Jämförelseindex>
    </Jämförelseindex>
    <FinansiellaInstrument>
      <FinansielltInstrument>
        <Tillgångsslag_enligt_LVF_5_kap>Fondandel</Tillgångsslag_enligt_LVF_5_kap>
        <Instrumentnamn>Alfred Berg Income R (NOK)</Instrumentnamn>
        <ISIN-kod_instrument>SE0006261269</ISIN-kod_instrument>
        <Landkod_Emittent>SE</Landkod_Emittent>
        <Valuta>NOK</Valuta>
        <Antal>216977.9621</Antal>
        <Nominellt_belopp />
        <Kurs_som_använts_vid_värdering_av_instrumentet>142.9984</Kurs_som_använts_vid_värdering_av_instrumentet>
        <Valutakurs_instrument>0.9614</Valutakurs_instrument>
        <Marknadsvärde_instrument>29828400</Marknadsvärde_instrument>
        <Andel_av_fondförmögenhet_instrument>6.97</Andel_av_fondförmögenhet_instrument>
        <Bransch>
          <Branschkod_instrument>0</Branschkod_instrument>
          <Bransch_namn_instrument>Övrigt</Bransch_namn_instrument>
        </Bransch>
      </FinansielltInstrument>
      <FinansielltInstrument>
        <Tillgångsslag_enligt_LVF_5_kap>Fondandel</Tillgångsslag_enligt_LVF_5_kap>
        <Instrumentnamn>Alfred Berg Nordic High Yield Restricted R (NOK)</Instrumentnamn>
        <ISIN-kod_instrument>SE0014583738</ISIN-kod_instrument>
        <Landkod_Emittent>SE</Landkod_Emittent>
        <Valuta>NOK</Valuta>
        <Antal>245684.7576</Antal>
        <Nominellt_belopp />
        <Kurs_som_använts_vid_värdering_av_instrumentet>122.9543</Kurs_som_använts_vid_värdering_av_instrumentet>
        <Valutakurs_instrument>0.9614</Valutakurs_instrument>
        <Marknadsvärde_instrument>29040567</Marknadsvärde_instrument>
        <Andel_av_fondförmögenhet_instrument>6.78</Andel_av_fondförmögenhet_instrument>
        <Bransch>
          <Branschkod_instrument>0</Branschkod_instrument>
          <Bransch_namn_instrument>Övrigt</Bransch_namn_instrument>
        </Bransch>
      </FinansielltInstrument>
      <FinansielltInstrument>
        <Tillgångsslag_enligt_LVF_5_kap>Fondandel</Tillgångsslag_enligt_LVF_5_kap>
        <Instrumentnamn>Alfred Berg Nordic Investment Grade Long Duration R (NOK)</Instrumentnamn>
        <ISIN-kod_instrument>NO0010860166</ISIN-kod_instrument>
        <Landkod_Emittent>NO</Landkod_Emittent>
        <Valuta>NOK</Valuta>
        <Antal>565030.5505</Antal>
        <Nominellt_belopp />
        <Kurs_som_använts_vid_värdering_av_instrumentet>91.8473</Kurs_som_använts_vid_värdering_av_instrumentet>
        <Valutakurs_instrument>0.9614</Valutakurs_instrument>
        <Marknadsvärde_instrument>49890916</Marknadsvärde_instrument>
        <Andel_av_fondförmögenhet_instrument>11.65</Andel_av_fondförmögenhet_instrument>
        <Bransch>
          <Branschkod_instrument>0</Branschkod_instrument>
          <Bransch_namn_instrument>Övrigt</Bransch_namn_instrument>
        </Bransch>
      </FinansielltInstrument>
      <FinansielltInstrument>
        <Tillgångsslag_enligt_LVF_5_kap>Fondandel</Tillgångsslag_enligt_LVF_5_kap>
        <Instrumentnamn>Alfred Berg Nordic Investment Grade Mid Duration R (NOK)</Instrumentnamn>
        <ISIN-kod_instrument>NO0010811920</ISIN-kod_instrument>
        <Landkod_Emittent>NO</Landkod_Emittent>
        <Valuta>NOK</Valuta>
        <Antal>631246.3832</Antal>
        <Nominellt_belopp />
        <Kurs_som_använts_vid_värdering_av_instrumentet>105.1869</Kurs_som_använts_vid_värdering_av_instrumentet>
        <Valutakurs_instrument>0.9614</Valutakurs_instrument>
        <Marknadsvärde_instrument>63832773</Marknadsvärde_instrument>
        <Andel_av_fondförmögenhet_instrument>14.91</Andel_av_fondförmögenhet_instrument>
        <Bransch>
          <Branschkod_instrument>0</Branschkod_instrument>
          <Bransch_namn_instrument>Övrigt</Bransch_namn_instrument>
        </Bransch>
      </FinansielltInstrument>
      <FinansielltInstrument>
        <Tillgångsslag_enligt_LVF_5_kap>Fondandel</Tillgångsslag_enligt_LVF_5_kap>
        <Instrumentnamn>Alfred Berg Nordic Investment Grade R (NOK)</Instrumentnamn>
        <ISIN-kod_instrument>NO0010752538</ISIN-kod_instrument>
        <Landkod_Emittent>NO</Landkod_Emittent>
        <Valuta>NOK</Valuta>
        <Antal>427020.2094</Antal>
        <Nominellt_belopp />
        <Kurs_som_använts_vid_värdering_av_instrumentet>112.4833</Kurs_som_använts_vid_värdering_av_instrumentet>
        <Valutakurs_instrument>0.9614</Valutakurs_instrument>
        <Marknadsvärde_instrument>46176353</Marknadsvärde_instrument>
        <Andel_av_fondförmögenhet_instrument>10.78</Andel_av_fondförmögenhet_instrument>
        <Bransch>
          <Branschkod_instrument>0</Branschkod_instrument>
          <Bransch_namn_instrument>Övrigt</Bransch_namn_instrument>
        </Bransch>
      </FinansielltInstrument>
      <FinansielltInstrument>
        <Tillgångsslag_enligt_LVF_5_kap>Fondandel</Tillgångsslag_enligt_LVF_5_kap>
        <Instrumentnamn>Alfred Berg Nordisk Ansvarlig Kapital</Instrumentnamn>
        <ISIN-kod_instrument>SE0014583738</ISIN-kod_instrument>
        <Landkod_Emittent>NO</Landkod_Emittent>
        <Valuta>NOK</Valuta>
        <Antal>193402.0317</Antal>
        <Nominellt_belopp />
        <Kurs_som_använts_vid_värdering_av_instrumentet>115.576</Kurs_som_använts_vid_värdering_av_instrumentet>
        <Valutakurs_instrument>0.9614</Valutakurs_instrument>
        <Marknadsvärde_instrument>21488784</Marknadsvärde_instrument>
        <Andel_av_fondförmögenhet_instrument>5.02</Andel_av_fondförmögenhet_instrument>
        <Bransch>
          <Branschkod_instrument>0</Branschkod_instrument>
          <Bransch_namn_instrument>Övrigt</Bransch_namn_instrument>
        </Bransch>
      </FinansielltInstrument>
      <FinansielltInstrument>
        <Tillgångsslag_enligt_LVF_5_kap>Fondandel</Tillgångsslag_enligt_LVF_5_kap>
        <Instrumentnamn>Alfred Berg Nordisk Likviditet Pluss R (NOK)</Instrumentnamn>
        <ISIN-kod_instrument>NO0010830409</ISIN-kod_instrument>
        <Landkod_Emittent>NO</Landkod_Emittent>
        <Valuta>NOK</Valuta>
        <Antal>597749.9104</Antal>
        <Nominellt_belopp />
        <Kurs_som_använts_vid_värdering_av_instrumentet>107.9128</Kurs_som_använts_vid_värdering_av_instrumentet>
        <Valutakurs_instrument>0.9614</Valutakurs_instrument>
        <Marknadsvärde_instrument>62011985</Marknadsvärde_instrument>
        <Andel_av_fondförmögenhet_instrument>14.48</Andel_av_fondförmögenhet_instrument>
        <Bransch>
          <Branschkod_instrument>0</Branschkod_instrument>
          <Bransch_namn_instrument>Övrigt</Bransch_namn_instrument>
        </Bransch>
      </FinansielltInstrument>
      <FinansielltInstrument>
        <Tillgångsslag_enligt_LVF_5_kap>Fondandel</Tillgångsslag_enligt_LVF_5_kap>
        <Instrumentnamn>Fondsfinans Kreditt B</Instrumentnamn>
        <ISIN-kod_instrument>NO0013168765</ISIN-kod_instrument>
        <Landkod_Emittent>NO</Landkod_Emittent>
        <Valuta>NOK</Valuta>
        <Antal>3743.7448</Antal>
        <Nominellt_belopp />
        <Kurs_som_använts_vid_värdering_av_instrumentet>11961.26</Kurs_som_använts_vid_värdering_av_instrumentet>
        <Valutakurs_instrument>0.9614</Valutakurs_instrument>
        <Marknadsvärde_instrument>43049322</Marknadsvärde_instrument>
        <Andel_av_fondförmögenhet_instrument>10.05</Andel_av_fondförmögenhet_instrument>
        <Bransch>
          <Branschkod_instrument>0</Branschkod_instrument>
          <Bransch_namn_instrument>Övrigt</Bransch_namn_instrument>
        </Bransch>
      </FinansielltInstrument>
      <FinansielltInstrument>
        <Tillgångsslag_enligt_LVF_5_kap>Fondandel</Tillgångsslag_enligt_LVF_5_kap>
        <Instrumentnamn>Holberg Obligasjon Norden A</Instrumentnamn>
        <ISIN-kod_instrument>NO0010154453</ISIN-kod_instrument>
        <Landkod_Emittent>NO</Landkod_Emittent>
        <Valuta>NOK</Valuta>
        <Antal>684327.4845</Antal>
        <Nominellt_belopp />
        <Kurs_som_använts_vid_värdering_av_instrumentet>108.0053</Kurs_som_använts_vid_värdering_av_instrumentet>
        <Valutakurs_instrument>0.9614</Valutakurs_instrument>
        <Marknadsvärde_instrument>71054600</Marknadsvärde_instrument>
        <Andel_av_fondförmögenhet_instrument>16.59</Andel_av_fondförmögenhet_instrument>
        <Bransch>
          <Branschkod_instrument>0</Branschkod_instrument>
          <Bransch_namn_instrument>Övrigt</Bransch_namn_instrument>
        </Bransch>
      </FinansielltInstrument>
    </FinansiellaInstrument>
  </Fondinformation>
  <Fondinformation />
</VärdepappersfondInnehav>